README.md
setup.py
data_tap/__init__.py
data_tap/base_tap.py
data_tap/decorators.py
data_tap/utils.py
data_tap.egg-info/PKG-INFO
data_tap.egg-info/SOURCES.txt
data_tap.egg-info/dependency_links.txt
data_tap.egg-info/requires.txt
data_tap.egg-info/top_level.txt
data_tap/google_tap/__init__.py
data_tap/google_tap/google_analytics.py
data_tap/google_tap/google_seach_console.py
tests/__init__.py
tests/base_tap/__init__.py
tests/base_tap/test_base.py
tests/google_tap/__init__.py
tests/google_tap/test_google_analytics.py