Metadata-Version: 2.1
Name: data-tap
Version: 0.0.7
Summary: A python wrapper that connects to multiple 3rd party resources for AWS.
Home-page: https://github.com/DirksCGM/data-tap
Author: DirkSCGM
Author-email: dirkscgm@gmail.com
License: UNKNOWN
Keywords: aws,s3,google,google analytics,google search console,data,pipeline
Platform: UNKNOWN
Classifier: Programming Language :: Python :: 3 :: Only
Requires-Python: >=3
